pyPhotonLLTFContrast/__init__.py
pyPhotonLLTFContrast/config (2130-5ZZFHQ2's conflicted copy 2022-10-24).json
pyPhotonLLTFContrast/config.json
pyPhotonLLTFContrast/driver.py
pyPhotonLLTFContrast/driver_virtual.py
pyPhotonLLTFContrast/main.py
pyPhotonLLTFContrast-0.4.dist-info/METADATA
pyPhotonLLTFContrast-0.4.dist-info/WHEEL
pyPhotonLLTFContrast-0.4.dist-info/entry_points.txt
pyPhotonLLTFContrast-0.4.dist-info/top_level.txt
pyPhotonLLTFContrast-0.4.dist-info/RECORD
