Metadata-Version: 2.1
Name: pyPhotonLLTFContrast
Version: 0.4
Summary: A python library/GUI to access and control the LLTF Contrast filters made by Photon.
Home-page: https://github.com/MicheleCotrufo/
Author: Michele Cotrufo
Author-email: michele.cotrufo@gmail.com
License: MIT
Platform: UNKNOWN
